simplePyQt5/__init__.py
simplePyQt5/horizontalWidget.py
simplePyQt5/insertDialog.py
simplePyQt5/leftRightWidget.py
simplePyQt5/okCancelWidget.py
simplePyQt5/styleApplier.py
simplePyQt5/tableWidget.py
simplePyQt5/topLabelBottomWidget.py
simplePyQt5/topLeftRightWidget.py
simplePyQt5/verticalWidget.py
simplePyQt5-0.0.1.dist-info/LICENSE
simplePyQt5-0.0.1.dist-info/METADATA
simplePyQt5-0.0.1.dist-info/WHEEL
simplePyQt5-0.0.1.dist-info/top_level.txt
simplePyQt5-0.0.1.dist-info/RECORD
