Metadata-Version: 2.1
Name: simplePyQt5
Version: 0.0.1
Summary: simple PyQt5
Home-page: https://github.com/yjg30737/simplePyQt5.git
Author: Jung Gyu Yoon
Author-email: yjg30737@gmail.com
License: MIT
Platform: UNKNOWN
License-File: LICENSE
